bb84/__init__.py
bb84/communication.py
bb84/error_correction.py
bb84/experiments.py
bb84/key_distribution.py
bb84/metrics.py
bb84/noise_simulation.py
bb84/quantum_utilities.py
bb84/visualization.py
bb84/attacks/__init__.py
bb84/attacks/intercept_resend.py
bb84/protocols/__init__.py
bb84/protocols/base.py
bb84/protocols/bitwise.py
bb84/protocols/majority_vote.py
bb84/protocols/standard.py
quantum_bb84simulator-1.2.1.dist-info/licenses/LICENSE
quantum_bb84simulator-1.2.1.dist-info/licenses/LICENSE.txt
quantum_bb84simulator-1.2.1.dist-info/METADATA
quantum_bb84simulator-1.2.1.dist-info/WHEEL
quantum_bb84simulator-1.2.1.dist-info/entry_points.txt
quantum_bb84simulator-1.2.1.dist-info/top_level.txt
quantum_bb84simulator-1.2.1.dist-info/RECORD
